setup.py
tornadoes/__init__.py
tornadoes/models.py
tornadoes.egg-info/PKG-INFO
tornadoes.egg-info/SOURCES.txt
tornadoes.egg-info/dependency_links.txt
tornadoes.egg-info/pbr.json
tornadoes.egg-info/requires.txt
tornadoes.egg-info/top_level.txt
tornadoes.egg-info/zip-safe
tornadoes/tests/__init__.py
tornadoes/tests/unit/__init__.py
tornadoes/tests/unit/test_tornadoes.py