Metadata-Version: 1.1
Name: tornadoes
Version: 2.4.2
Summary: A tornado-powered python library that provides asynchronous access to elasticsearch.
Home-page: http://github.com/globocom/tornado-es
Author: Team Search of globo.com
Author-email: busca@corp.globo.com
License: MIT
Download-URL: http://github.com/globocom/tornado-es
Platform: UNKNOWN
Classifier: Development Status :: 4 - Beta
Classifier: Intended Audience :: Developers
Classifier: License :: OSI Approved :: MIT License
Classifier: Natural Language :: English
Classifier: Operating System :: Unix
Classifier: Operating System :: OS Independent
Classifier: Programming Language :: Python :: 2.7
Classifier: Programming Language :: Python :: 3.4
Classifier: Programming Language :: Python :: Implementation :: PyPy
